kenverters/__init__.py
kenverters-0.0.0.dist-info/METADATA
kenverters-0.0.0.dist-info/WHEEL
kenverters-0.0.0.dist-info/top_level.txt
kenverters-0.0.0.dist-info/RECORD
