Metadata-Version: 2.1
Name: kenverters
Version: 0.0.0
Summary: Coming soon
Author-email: Valerie Faucon-Morin <valerie.fauconmorin@kensho.com>
